[
  {
    "book_name": "Bangladesh and world identity",
    "book_info": [
      {
        "chapter_count": "1",
        "chapter_name": "ইতিহাস পরিচিতি",
        "chapterInfo": {
          "chapter_file_name": "12850420",
          "chapter_link": "https://github.com/hackbypdf/l360/files/12850420/book.pdf"
        },
        "guideInfo": {
          "guide_file_name": "12850423",
          "guide_pdf_link": "https://github.com/hackbypdf/l360/files/12850423/guide.pdf"
        },
        "noteInfo": [],
        "suggestionInfo": []
      },
      {
        "chapter_count": "2",
        "chapter_name": "বিশ্বসভ্যতা",
        "chapterInfo": {
          "chapter_file_name": "12850439",
          "chapter_link": "https://github.com/hackbypdf/l360/files/12850439/book.pdf"
        },
        "guideInfo": {
          "guide_file_name": "12850440",
          "guide_pdf_link": "https://github.com/hackbypdf/l360/files/12850440/guide.pdf"
        },
        "noteInfo": [],
        "suggestionInfo": []
      },
      {
        "chapter_count": "3",
        "chapter_name": "প্রাচীন বাংলার জনপদ",
        "chapterInfo": {
          "chapter_file_name": "12850424",
          "chapter_link": "https://github.com/hackbypdf/l360/files/12850424/book.pdf"
        },
        "guideInfo": {
          "guide_file_name": "12850425",
          "guide_pdf_link": "https://github.com/hackbypdf/l360/files/12850425/guide.pdf"
        },
        "noteInfo": [],
        "suggestionInfo": []
      },
      {
        "chapter_count": "4",
        "chapter_name": "প্রাচীন বাংলার রাজনৈতিক ইতিহাস",
        "chapterInfo": {
          "chapter_file_name": "12850426",
          "chapter_link": "https://github.com/hackbypdf/l360/files/12850426/book.pdf"
        },
        "guideInfo": {
          "guide_file_name": "12850428",
          "guide_pdf_link": "https://github.com/hackbypdf/l360/files/12850428/guide.pdf"
        },
        "noteInfo": [],
        "suggestionInfo": []
      },
      {
        "chapter_count": "5",
        "chapter_name": "প্রাচীন বাংলার সামাজিক, অর্থনৈতিক ও সাংস্কৃতিক ইতিহাস",
        "chapterInfo": {
          "chapter_file_name": "12850429",
          "chapter_link": "https://github.com/hackbypdf/l360/files/12850429/book.pdf"
        },
        "guideInfo": {
          "guide_file_name": "12850432",
          "guide_pdf_link": "https://github.com/hackbypdf/l360/files/12850432/guide.pdf"
        },
        "noteInfo": [],
        "suggestionInfo": []
      },
      {
        "chapter_count": "6",
        "chapter_name": "মধ্যযুগের বাংলার রাজনৈতিক ইতিহাস",
        "chapterInfo": {
          "chapter_file_name": "12850443",
          "chapter_link": "https://github.com/hackbypdf/l360/files/12850443/book.pdf"
        },
        "guideInfo": {
          "guide_file_name": "12850446",
          "guide_pdf_link": "https://github.com/hackbypdf/l360/files/12850446/guide.pdf"
        },
        "noteInfo": [],
        "suggestionInfo": []
      },
      {
        "chapter_count": "7",
        "chapter_name": "মধ্যযুগের বাংলার সামাজিক, অর্থনৈতিক ও সাংস্কৃতিক ইতিহাস",
        "chapterInfo": {
          "chapter_file_name": "12850447",
          "chapter_link": "https://github.com/hackbypdf/l360/files/12850447/book.pdf"
        },
        "guideInfo": {
          "guide_file_name": "12850450",
          "guide_pdf_link": "https://github.com/hackbypdf/l360/files/12850450/guide.pdf"
        },
        "noteInfo": [],
        "suggestionInfo": []
      },
      {
        "chapter_count": "8",
        "chapter_name": "বাংলায় ইংরেজ শাসনের সূচনাপর্ব",
        "chapterInfo": {
          "chapter_file_name": "12850435",
          "chapter_link": "https://github.com/hackbypdf/l360/files/12850435/book.pdf"
        },
        "guideInfo": {
          "guide_file_name": "12850437",
          "guide_pdf_link": "https://github.com/hackbypdf/l360/files/12850437/guide.pdf"
        },
        "noteInfo": [],
        "suggestionInfo": []
      },
      {
        "chapter_count": "9",
        "chapter_name": "ইংরেজ শাসন আমলে বাংলায় প্রতিরোধ, নবজাগরণ ও সংস্কার আন্দোলন",
        "chapterInfo": {
          "chapter_file_name": "12850411",
          "chapter_link": "https://github.com/hackbypdf/l360/files/12850411/book.pdf"
        },
        "guideInfo": {
          "guide_file_name": "12850413",
          "guide_pdf_link": "https://github.com/hackbypdf/l360/files/12850413/guide.pdf"
        },
        "noteInfo": [],
        "suggestionInfo": []
      },
      {
        "chapter_count": "10",
        "chapter_name": "ইংরেজ শাসন আমলে বাংলার স্বাধিকার আন্দোলন",
        "chapterInfo": {
          "chapter_file_name": "12850416",
          "chapter_link": "https://github.com/hackbypdf/l360/files/12850416/book.pdf"
        },
        "guideInfo": {
          "guide_file_name": "12850418",
          "guide_pdf_link": "https://github.com/hackbypdf/l360/files/12850418/guide.pdf"
        },
        "noteInfo": [],
        "suggestionInfo": []
      },
      {
        "chapter_count": "11",
        "chapter_name": "ভাষা আন্দোলন ও পরবর্তী রাজনৈতিক ঘটনাপ্রবাহ",
        "chapterInfo": {
          "chapter_file_name": "12850441",
          "chapter_link": "https://github.com/hackbypdf/l360/files/12850441/book.pdf"
        },
        "guideInfo": {
          "guide_file_name": "12850442",
          "guide_pdf_link": "https://github.com/hackbypdf/l360/files/12850442/guide.pdf"
        },
        "noteInfo": [],
        "suggestionInfo": []
      },
      {
        "chapter_count": "12",
        "chapter_name": "সামরিক শাসন ও স্বাধিকার আন্দোলন",
        "chapterInfo": {
          "chapter_file_name": "12850460",
          "chapter_link": "https://github.com/hackbypdf/l360/files/12850460/book.pdf"
        },
        "guideInfo": {
          "guide_file_name": "12850462",
          "guide_pdf_link": "https://github.com/hackbypdf/l360/files/12850462/guide.pdf"
        },
        "noteInfo": [],
        "suggestionInfo": []
      },
      {
        "chapter_count": "13",
        "chapter_name": "সত্তরের নির্বাচন এবং মুক্তিযুদ্ধ",
        "chapterInfo": {
          "chapter_file_name": "12850451",
          "chapter_link": "https://github.com/hackbypdf/l360/files/12850451/book.pdf"
        },
        "guideInfo": {
          "guide_file_name": "12850454",
          "guide_pdf_link": "https://github.com/hackbypdf/l360/files/12850454/guide.pdf"
        },
        "noteInfo": [],
        "suggestionInfo": []
      },
      {
        "chapter_count": "14",
        "chapter_name": "বঙ্গবন্ধু শেখ মুজিবুর রহমানের শাসনকাল",
        "chapterInfo": {
          "chapter_file_name": "12850433",
          "chapter_link": "https://github.com/hackbypdf/l360/files/12850433/book.pdf"
        },
        "guideInfo": {
          "guide_file_name": "12850434",
          "guide_pdf_link": "https://github.com/hackbypdf/l360/files/12850434/guide.pdf"
        },
        "noteInfo": [],
        "suggestionInfo": []
      },
      {
        "chapter_count": "15",
        "chapter_name": "সামরিক শাসন ও পরবর্তী ঘটনাপ্রবাহ",
        "chapterInfo": {
          "chapter_file_name": "12850457",
          "chapter_link": "https://github.com/hackbypdf/l360/files/12850457/book.pdf"
        },
        "guideInfo": {
          "guide_file_name": "12850459",
          "guide_pdf_link": "https://github.com/hackbypdf/l360/files/12850459/guide.pdf"
        },
        "noteInfo": [],
        "suggestionInfo": []
      }
      
    ]
  }
]
